seometa/__init__.py
seometa/seo.py
seometa/seometa.py
seometa-0.0.1.7.dist-info/METADATA
seometa-0.0.1.7.dist-info/WHEEL
seometa-0.0.1.7.dist-info/top_level.txt
seometa-0.0.1.7.dist-info/RECORD
