Metadata-Version: 2.1
Name: seometa
Version: 0.0.1.7
Summary: Get SEO Meta-data from Websites
Author: Aymane Elhattab
Author-email: <aymane.elhattab.master@gmail.com>
License: UNKNOWN
Keywords: seo,meta data,website,data scraper,data,data mining
Platform: UNKNOWN
Classifier: Development Status :: 1 - Planning
Classifier: Intended Audience :: Developers
Classifier: Programming Language :: Python :: 3
Classifier: Operating System :: Unix
Classifier: Operating System :: MacOS :: MacOS X
Classifier: Operating System :: Microsoft :: Windows
Requires-Dist: beautifulsoup4
Requires-Dist: requests
